neuralplex/__about__.py
neuralplex/__init__.py
neuralplex/layer.py
neuralplex/network.py
neuralplex/neuron.py
neuralplex/utils.py
neuralplex-0.1.5.dist-info/METADATA
neuralplex-0.1.5.dist-info/WHEEL
neuralplex-0.1.5.dist-info/licenses/LICENSE
neuralplex-0.1.5.dist-info/RECORD
