Metadata-Version: 2.4
Name: neuralplex
Version: 0.1.5
Summary: An object oriented neural network implementation.
Project-URL: Homepage, https://github.com/far-analytics/neuralplex
Project-URL: Issues, https://github.com/far-analytics/neuralplex/issues
Author-email: FAR Analytics & Research <adpatter2000@gmail.com>
License-File: LICENSE
Classifier: License :: OSI Approved :: MIT License
Classifier: Operating System :: OS Independent
Classifier: Programming Language :: Python :: 3
Requires-Python: >=3.11
Requires-Dist: scikit-learn
Requires-Dist: scipy
